{
  "accentColor": "{{appsmith.theme.colors.primaryColor}}",
  "animateLoading": "true",
  "borderRadius": "{{appsmith.theme.borderRadius.appBorderRadius}}",
  "bottomRow": 29,
  "boxShadow": "{{appsmith.theme.boxShadow.appBoxShadow}}",
  "childStylesheet": {
    "button": {
      "borderRadius": "{{appsmith.theme.borderRadius.appBorderRadius}}",
      "boxShadow": "none",
      "buttonColor": "{{appsmith.theme.colors.primaryColor}}"
    },
    "iconButton": {
      "borderRadius": "{{appsmith.theme.borderRadius.appBorderRadius}}",
      "boxShadow": "none",
      "buttonColor": "{{appsmith.theme.colors.primaryColor}}"
    },
    "menuButton": {
      "borderRadius": "{{appsmith.theme.borderRadius.appBorderRadius}}",
      "boxShadow": "none",
      "menuColor": "{{appsmith.theme.colors.primaryColor}}"
    }
  },
  "columnOrder": [
    "Name",
    "DOB",
    "Gender",
    "rowIndex"
  ],
  "columnSizeMap": {
    "status": 75,
    "step": 62,
    "task": 245
  },
  "defaultPageSize": 0,
  "defaultSelectedRow": "0",
  "delimiter": ",",
  "derivedColumns": {},
  "displayName": "Table",
  "dynamicBindingPathList": [
    {
      "key": "accentColor"
    },
    {
      "key": "borderRadius"
    },
    {
      "key": "boxShadow"
    },
    {
      "key": "childStylesheet.button.buttonColor"
    },
    {
      "key": "childStylesheet.button.borderRadius"
    },
    {
      "key": "childStylesheet.menuButton.menuColor"
    },
    {
      "key": "childStylesheet.menuButton.borderRadius"
    },
    {
      "key": "childStylesheet.iconButton.buttonColor"
    },
    {
      "key": "childStylesheet.iconButton.borderRadius"
    },
    {
      "key": "tableData"
    },
    {
      "key": "primaryColumns.rowIndex.computedValue"
    },
    {
      "key": "primaryColumns.Name.computedValue"
    },
    {
      "key": "primaryColumns.DOB.computedValue"
    },
    {
      "key": "primaryColumns.Gender.computedValue"
    }
  ],
  "dynamicPropertyPathList": [
    {
      "key": "animateLoading"
    }
  ],
  "dynamicTriggerPathList": [],
  "enableClientSideSearch": true,
  "hideCard": false,
  "horizontalAlignment": "LEFT",
  "iconSVG": "/static/media/icon.db8a9cbd2acd22a31ea91cc37ea2a46c.svg",
  "isDeprecated": false,
  "isLoading": false,
  "isSortable": true,
  "isVisible": true,
  "isVisibleDownload": true,
  "isVisibleFilters": true,
  "isVisiblePagination": true,
  "isVisibleSearch": true,
  "key": "iftra34q4u",
  "label": "Data",
  "leftColumn": 2,
  "parentColumnSpace": 12.1875,
  "parentId": "0",
  "parentRowSpace": 10,
  "primaryColumns": {
    "DOB": {
      "cellBackground": "",
      "columnType": "text",
      "computedValue": "{{Table1.sanitizedTableData.map((currentRow) => ( currentRow.DOB))}}",
      "enableFilter": true,
      "enableSort": true,
      "horizontalAlignment": "LEFT",
      "id": "DOB",
      "index": 1,
      "isCellVisible": true,
      "isDerived": false,
      "isDisabled": false,
      "isVisible": true,
      "label": "DOB",
      "textColor": "",
      "textSize": "0.875rem",
      "verticalAlignment": "CENTER",
      "width": 150
    },
    "Gender": {
      "cellBackground": "",
      "columnType": "text",
      "computedValue": "{{Table1.sanitizedTableData.map((currentRow) => ( currentRow.Gender))}}",
      "enableFilter": true,
      "enableSort": true,
      "horizontalAlignment": "LEFT",
      "id": "Gender",
      "index": 2,
      "isCellVisible": true,
      "isDerived": false,
      "isDisabled": false,
      "isVisible": true,
      "label": "Gender",
      "textColor": "",
      "textSize": "0.875rem",
      "verticalAlignment": "CENTER",
      "width": 150
    },
    "Name": {
      "cellBackground": "",
      "columnType": "text",
      "computedValue": "{{Table1.sanitizedTableData.map((currentRow) => ( currentRow.Name))}}",
      "enableFilter": true,
      "enableSort": true,
      "horizontalAlignment": "LEFT",
      "id": "Name",
      "index": 0,
      "isCellVisible": true,
      "isDerived": false,
      "isDisabled": false,
      "isVisible": true,
      "label": "Name",
      "textColor": "",
      "textSize": "0.875rem",
      "verticalAlignment": "CENTER",
      "width": 150
    },
    "rowIndex": {
      "columnType": "text",
      "computedValue": "{{Table1.sanitizedTableData.map((currentRow) => ( currentRow.rowIndex))}}",
      "enableFilter": true,
      "enableSort": true,
      "horizontalAlignment": "LEFT",
      "id": "rowIndex",
      "index": 4,
      "isCellVisible": true,
      "isDerived": false,
      "isDisabled": false,
      "isVisible": true,
      "label": "rowIndex",
      "textSize": "0.875rem",
      "verticalAlignment": "CENTER",
      "width": 150
    }
  },
  "renderMode": "CANVAS",
  "rightColumn": 63,
  "searchKey": "",
  "searchTags": [
    "datagrid"
  ],
  "tableData": "{{Query1.data}}",
  "textSize": "0.875rem",
  "topRow": 1,
  "totalRecordsCount": 0,
  "type": "TABLE_WIDGET",
  "version": 3,
  "verticalAlignment": "CENTER",
  "widgetId": "cteg85dcmm",
  "widgetName": "Table1"
}